vpadanalyzer/__init__.py
vpadanalyzer/arguments.py
vpadanalyzer/paths.py
vpadanalyzer/synthesis.py
vpadanalyzer/config/__init__.py
vpadanalyzer/config/abc.script
vpadanalyzer/config/gscl45nm.lib
verilog_pad_analyzer-0.0.7.dist-info/LICENSE
verilog_pad_analyzer-0.0.7.dist-info/METADATA
verilog_pad_analyzer-0.0.7.dist-info/WHEEL
verilog_pad_analyzer-0.0.7.dist-info/top_level.txt
verilog_pad_analyzer-0.0.7.dist-info/RECORD
