Metadata-Version: 2.1
Name: verilog-pad-analyzer
Version: 0.0.7
Summary: VerilogPADAnalyzer is a Python application designed to analyze and report the
Home-page: https://github.com/MortezaRezaalipour/VerilogPADAnalyzer
Author: Morteza Rezaalipour (MorellRAP)
Author-email: <rezaalipour.usi@gmail.com>
Keywords: python,verilog,PAD,synthesis,analysis,circuit,EDA,simulation,hardware,design
Classifier: Development Status :: 4 - Beta
Classifier: Intended Audience :: Developers
Classifier: Programming Language :: Python :: 3
Classifier: Operating System :: Unix
Classifier: Operating System :: MacOS :: MacOS X
Classifier: Operating System :: Microsoft :: Windows
License-File: LICENSE
